aioconsole/__init__.py
aioconsole/__main__.py
aioconsole/apython.py
aioconsole/command.py
aioconsole/compat.py
aioconsole/console.py
aioconsole/events.py
aioconsole/execute.py
aioconsole/rlwrap.py
aioconsole/server.py
aioconsole/stream.py
aioconsole-0.8.2.dist-info/LICENSE
aioconsole-0.8.2.dist-info/METADATA
aioconsole-0.8.2.dist-info/WHEEL
aioconsole-0.8.2.dist-info/entry_points.txt
aioconsole-0.8.2.dist-info/top_level.txt
aioconsole-0.8.2.dist-info/RECORD
