Metadata-Version: 2.1
Name: aioconsole
Version: 0.8.2
Summary: Asynchronous console and interfaces for asyncio
Author-email: Vincent Michel <vxgmichel@gmail.com>
License: GPL-3.0-or-later
Project-URL: Homepage, https://github.com/vxgmichel/aioconsole
Classifier: License :: OSI Approved :: GNU General Public License v3 or later (GPLv3+)
Classifier: Programming Language :: Python
Classifier: Programming Language :: Python :: 3
Classifier: Programming Language :: Python :: 3.8
Classifier: Programming Language :: Python :: 3.9
Classifier: Programming Language :: Python :: 3.10
Classifier: Programming Language :: Python :: 3.11
Classifier: Programming Language :: Python :: 3.12
Classifier: Programming Language :: Python :: 3.13
Classifier: Programming Language :: Python :: 3.14
Classifier: Programming Language :: Python :: 3 :: Only
Requires-Python: >=3.8
License-File: LICENSE
Provides-Extra: dev
Requires-Dist: pytest; extra == "dev"
Requires-Dist: pytest-asyncio; extra == "dev"
Requires-Dist: pytest-cov; extra == "dev"
Requires-Dist: pytest-repeat; extra == "dev"
Requires-Dist: uvloop; (platform_python_implementation != "PyPy" and sys_platform != "win32") and extra == "dev"
